nightskycam_scorer/__init__.py
nightskycam_scorer/annotator/__init__.py
nightskycam_scorer/annotator/app.py
nightskycam_scorer/annotator/cli.py
nightskycam_scorer/constants.py
nightskycam_scorer/model/__init__.py
nightskycam_scorer/model/cli.py
nightskycam_scorer/model/data.py
nightskycam_scorer/model/evaluate.py
nightskycam_scorer/model/evaluate_cli.py
nightskycam_scorer/model/infer.py
nightskycam_scorer/model/model.py
nightskycam_scorer/model/py.typed
nightskycam_scorer/model/train.py
nightskycam_scorer/model/transforms.py
nightskycam_scorer/utils.py
nightskycam_scorer-0.2.1.dist-info/METADATA
nightskycam_scorer-0.2.1.dist-info/WHEEL
nightskycam_scorer-0.2.1.dist-info/entry_points.txt
nightskycam_scorer-0.2.1.dist-info/RECORD
