Metadata-Version: 2.4
Name: nightskycam-scorer
Version: 0.2.1
Summary: Binary classifier for night-sky image quality (e.g. clear vs unsuitable).
Author: Vincent Berenz
Author-email: vincent.berenz@tuebingen.mpg.de
Requires-Python: >=3.12,<3.15
Classifier: Programming Language :: Python :: 3
Classifier: Programming Language :: Python :: 3.12
Classifier: Programming Language :: Python :: 3.13
Classifier: Programming Language :: Python :: 3.14
Requires-Dist: flask (>=3.1.2,<4.0.0)
Requires-Dist: numpy (>=2.2,<2.3.0)
Requires-Dist: pillow (>=12.0.0,<13.0.0)
Requires-Dist: torch (>=2.9.1,<3.0.0)
Requires-Dist: torchvision (>=0.24.1,<0.25.0)
